llama_index/llms/clarifai/__init__.py
llama_index/llms/clarifai/base.py
llama_index_llms_clarifai-0.4.1.dist-info/METADATA
llama_index_llms_clarifai-0.4.1.dist-info/WHEEL
llama_index_llms_clarifai-0.4.1.dist-info/licenses/LICENSE
llama_index_llms_clarifai-0.4.1.dist-info/RECORD
