Metadata-Version: 2.4
Name: llama-index-llms-clarifai
Version: 0.4.1
Summary: llama-index llms clarifai integration
Author-email: Your Name <you@example.com>
License-Expression: MIT
License-File: LICENSE
Requires-Python: <4.0,>=3.9
Requires-Dist: clarifai<11,>=10.0.1
Requires-Dist: llama-index-core<0.15,>=0.13.0
